fpga/src/j1_sama.v
/*
Copyright (c)  2011
    James Bowman  All rights reserved.

Redistribution and use in source and binary forms, with or without
modification, are permitted provided that the following conditions
are met:
1. Redistributions of source code must retain the above copyright
  notice, this list of conditions and the following disclaimer.
2. Redistributions in binary form must reproduce the above copyright
  notice, this list of conditions and the following disclaimer in the
  documentation and/or other materials provided with the distribution.
3. Neither the name of James Bowman nor the names of its contributors
  may be used to endorse or promote products derived from this software
  without specific prior written permission.

THIS SOFTWARE IS PROVIDED BY THE COPYRIGHT HOLDERS AND CONTRIBUTORS
``AS IS'' AND ANY EXPRESS OR IMPLIED WARRANTIES, INCLUDING, BUT NOT
LIMITED TO, THE IMPLIED WARRANTIES OF MERCHANTABILITY AND FITNESS
FOR A PARTICULAR PURPOSE ARE DISCLAIMED.  IN NO EVENT SHALL THE
REGENTS OR CONTRIBUTORS BE LIABLE FOR ANY DIRECT, INDIRECT, INCIDENTAL,
SPECIAL, EXEMPLARY, OR CONSEQUENTIAL DAMAGES (INCLUDING, BUT NOT
LIMITED TO, PROCUREMENT OF SUBSTITUTE GOODS OR SERVICES; LOSS OF
USE, DATA, OR PROFITS; OR BUSINESS INTERRUPTION) HOWEVER CAUSED AND
ON ANY THEORY OF LIABILITY, WHETHER IN CONTRACT, STRICT LIABILITY,
OR TORT (INCLUDING NEGLIGENCE OR OTHERWISE) ARISING IN ANY WAY OUT
OF THE USE OF THIS SOFTWARE, EVEN IF ADVISED OF THE POSSIBILITY OF
SUCH DAMAGE.
*/

module j1(
  input sys_clk_i, 
  input sys_rst_i, 
  input [15:0] io_din,
  input int_req,

  output io_rd, 
  output io_wr, 
  output [15:0] io_addr, 
  output [15:0] io_dout
);

  reg req;  
  reg [15:0] insn;
  wire [15:0] immediate = { 1'b0, insn[14:0] };

  reg [4:0] dsp;  // Data stack pointer
  reg [4:0] _dsp;
  reg [15:0] st0; // Return stack pointer
  reg [15:0] _st0;
  wire _dstkW;     // D stack write

  reg [12:0] pc;
  reg [12:0] _pc;
  reg [4:0] rsp;
  reg [4:0] _rsp;
  reg _rstkW;     // R stack write
  reg [15:0] _rstkD;
  wire _ramWE;     // RAM write enable

  wire [15:0] pc_plus_1;
  assign pc_plus_1 = pc + 1'd1;

  // The D and R stacks
  reg [15:0] dstack[0:31];
  reg [15:0] rstack[0:31];
  always @(posedge sys_clk_i)
  begin
    if (_dstkW)
      dstack[_dsp] = st0;
    if (_rstkW)
      rstack[_rsp] = _rstkD;
  end
  wire [15:0] st1 = dstack[dsp];
  wire [15:0] rst0 = rstack[rsp];

  // st0sel is the ALU operation.  For branch and call the operation
  // is T, for 0branch it is N.  For ALU ops it is loaded from the instruction
  // field.
  reg [3:0] st0sel;
  always @*
  begin
    case (insn[14:13])
      2'b00: st0sel = 0;          // ubranch
      2'b10: st0sel = 0;          // call
      2'b01: st0sel = 1;          // 0branch
      2'b11: st0sel = insn[11:8]; // ALU
      default: st0sel = 4'bxxxx;
    endcase
  end


  // Papilio Pro: main memory to be infered instead of specified explitely.
   reg [15:0] ram[0:8191]; initial $readmemh("j1.hex", ram);
// ram_cpu  ram(
//		.address_a ( _pc ), // {} sds
//		.address_b ( _st0[15:1] ),
//		.clock ( sys_clk_i ),
//		.data_a ( 0 ),
//		.data_b ( st1 ),
//		.rden_a ( 1 ),
//		.rden_b ( |_st0[15:14] == 0 ),
//		.wren_a ( 0 ),
//		.wren_b ( _ramWE & (_st0[15:14] == 0) ),
//		.q_a ( insn ),
//		.q_b ( mem_din )
//);
//	
  reg [15:0] mem_din;
  always @(posedge sys_clk_i) begin
    // $monitor("insn_addr= %h, insn = %h, sp=%h, rp=%h, S=%h %h", pc, insn, dsp, rsp, st1, st0);
    insn <= ram[_pc];
    mem_din <= ram[_st0[15:1]];
    if (_ramWE & (_st0[15:14] ==0))
      ram[_st0[15:1]] <= st1[15:0];
  end


  // Compute the new value of T.
  always @*
  begin
    if (insn[15])
      _st0 = immediate;
    else
      case (st0sel)
        4'b0000: _st0 = st0;
        4'b0001: _st0 = st1;
        4'b0010: _st0 = st0 + st1;
        4'b0011: _st0 = st0 & st1;
        4'b0100: _st0 = st0 | st1;
        4'b0101: _st0 = st0 ^ st1;
        4'b0110: _st0 = ~st0;
        4'b0111: _st0 = {16{(st1 == st0)}};
        4'b1000: _st0 = {16{($signed(st1) < $signed(st0))}};
        4'b1001: _st0 = st1 >> st0[3:0];
        4'b1010: _st0 = st0 - 1'd1;
        4'b1011: _st0 = rst0;
        4'b1100: _st0 = |st0[15:14] ? io_din : mem_din;
        4'b1101: _st0 = st1 << st0[3:0];
        4'b1110: _st0 = {rsp, 3'b000, dsp};
        4'b1111: _st0 = {16{(st1 < st0)}};
        default: _st0 = 16'hxxxx;
      endcase
  end

  wire is_alu = (insn[15:13] == 3'b011);
  wire is_lit = (insn[15]);

  assign io_rd = (is_alu & (insn[11:8] == 4'hc));
  assign io_wr = _ramWE;
  assign io_addr = st0;
  assign io_dout = st1;

  assign _ramWE = is_alu & insn[5];
  assign _dstkW = is_lit | (is_alu & insn[7]);

  wire [1:0] dd = insn[1:0];  // D stack delta
  wire [1:0] rd = insn[3:2];  // R stack delta

  always @*
  begin
    //if (req)
    if (is_lit) begin                       // literal
      _dsp = dsp + 1'd1;
      _rsp = rsp;
      _rstkW = 1'd0;
      _rstkD = _pc;
    end else if (is_alu) begin
      _dsp = dsp + {dd[1], dd[1], dd[1], dd};
      _rsp = rsp + {rd[1], rd[1], rd[1], rd};
      _rstkW = insn[6];
      _rstkD = st0;
    end else begin                          // jump/call
      // predicated jump is like DROP
      if (insn[15:13] == 3'b001) begin
        _dsp = dsp - 1'd1;
      end else begin
        _dsp = dsp;
      end
      if (insn[15:13] == 3'b010) begin // call
        _rsp = rsp + 1'd1;
        _rstkW = 1;
        _rstkD = {pc_plus_1[14:0], 1'b0};
      end else begin
        _rsp = rsp;
        _rstkW = 1'd0;
        _rstkD = _pc;
      end
    end
  end

  always @*
  begin
    if (sys_rst_i)
      _pc = pc;
    else
      if ((insn[15:13] == 3'b000) |
          ((insn[15:13] == 3'b001) & (|st0 == 0)) |
          (insn[15:13] == 3'b010))
        _pc = insn[12:0];
      else if (is_alu & insn[12])
        _pc = rst0[15:1];
      else
        _pc = pc_plus_1;
  end

  always @(posedge sys_clk_i)
  begin
    if (sys_rst_i) begin
      req <= 0;
      pc <= 0;
      dsp <= 0;
      st0 <= 0;
      rsp <= 0;
    end else begin
      req <= int_req;
      pc <= _pc;
      dsp <= _dsp;
      st0 <= _st0;
      rsp <= _rsp;
    end
  end

endmodule // j1

fpga/src/j1-tb.v
/* J1 CPU Testbench */
`timescale 1ns/1ns
module j1_tb;

parameter tck = 20; ///< clock tick

reg clk, rst;
reg [15:0] io_din; // data input
reg int_req;
wire vsync;
wire io_rd;
wire io_wr;
wire [15:0] io_addr;
wire [15:0] io_dout;
wire [15:0] cpu_addr;

j1 cpu(
  clk, 
  rst,
  io_din,
  vsync, //int_req,

  io_rd,
  io_wr,
  io_addr, 
  io_dout
);

always #(tck/2) clk <= ~clk; // clocking device

reg [4:0] counter=0;
always @(negedge clk) begin  
  /*if (counter==8) 
    counter=0;
  else*/
   counter = counter+1;
end
assign vsync = 0; // (counter==8) ;//& clk ;

initial begin
  $dumpfile("j1.vcd");
  $dumpvars(-1, cpu, vsync, counter);
end

initial begin
  clk = 0; rst = 0; int_req=0;
  #(tck*2);
  rst = 1;
  #(tck*2);
  rst = 0;
  #(tck*11);
  int_req = 1;
  #(tck*1);
  int_req = 0;
  #(tck*55);
  $finish;
end

endmodule

fpga/firmware/j1.vcd
$date
	Tue Jul 20 18:50:19 2021
$end
$version
	Icarus Verilog
$end
$timescale
	1ns
$end
$scope module j1_tb $end
$scope module cpu $end
$var wire 1 ! _dstkW $end
$var wire 1 " _ramWE $end
$var wire 1 # int_req $end
$var wire 16 $ io_addr [15:0] $end
$var wire 16 % io_din [15:0] $end
$var wire 16 & io_dout [15:0] $end
$var wire 1 ' io_rd $end
$var wire 1 ( io_wr $end
$var wire 16 ) rst0 [15:0] $end
$var wire 16 * st1 [15:0] $end
$var wire 1 + sys_clk_i $end
$var wire 1 , sys_rst_i $end
$var wire 2 - rd [1:0] $end
$var wire 16 . pc_plus_1 [15:0] $end
$var wire 1 / is_lit $end
$var wire 1 0 is_alu $end
$var wire 16 1 immediate [15:0] $end
$var wire 2 2 dd [1:0] $end
$var reg 5 3 _dsp [4:0] $end
$var reg 13 4 _pc [12:0] $end
$var reg 5 5 _rsp [4:0] $end
$var reg 16 6 _rstkD [15:0] $end
$var reg 1 7 _rstkW $end
$var reg 16 8 _st0 [15:0] $end
$var reg 5 9 dsp [4:0] $end
$var reg 16 : insn [15:0] $end
$var reg 16 ; mem_din [15:0] $end
$var reg 13 < pc [12:0] $end
$var reg 1 = req $end
$var reg 5 > rsp [4:0] $end
$var reg 16 ? st0 [15:0] $end
$var reg 4 @ st0sel [3:0] $end
$upscope $end
$upscope $end
$scope module j1_tb $end
$var wire 1 # vsync $end
$upscope $end
$scope module j1_tb $end
$var reg 5 A counter [4:0] $end
$upscope $end
$enddefinitions $end
#0
$dumpvars
b1 A
bx @
bx ?
bx >
x=
bx <
bx ;
bx :
bx 9
bx 8
x7
bx 6
bx 5
bx 4
bx 3
bx 2
b0xxxxxxxxxxxxxxx 1
x0
x/
bx .
bx -
0,
0+
bx *
bx )
x(
x'
bx &
bx %
bx $
0#
x"
x!
$end
#10
0=
1+
#20
b10 A
0+
#30
1+
#40
b11 A
0+
1,
#50
b0 4
b0 6
07
b0 5
b0 3
b0 >
b0 $
b0 ?
b0 9
b1 .
b0 <
1+
#60
b100 A
0+
#70
0!
0'
0(
0"
b0 8
b0 @
b110011101111 1
00
0/
b11 2
b11 -
b110011101111 :
1+
#80
b101 A
0+
b110011101111 6
b110011101111 4
0,
#90
1!
b110011110000 6
b1 3
b10 8
b10 1
1/
b10 2
b0 -
b110011110000 4
b110011101111 ;
b1000000000000010 :
b110011110000 .
b110011101111 <
1+
#100
b110 A
0+
#110
b110011110001 6
b110011110001 4
b10 3
b11111010000000 8
b1 @
b11111010000000 1
b0 2
b10 $
b10 ?
b0 &
b0 *
b1 9
b110011110001 .
b110011110000 <
b10000 ;
b1011111010000000 :
1+
#120
b111 A
0+
#130
b1000010 8
b110011110010 6
b0 @
b1000010 1
b10 2
b110011110010 4
b11 3
bx ;
b1000000001000010 :
b11111010000000 $
b11111010000000 ?
b10 &
b10 *
b10 9
b110011110010 .
b110011110001 <
1+
#140
b1000 A
0+
#150
0!
b10101101011 4
b1100111100110 6
17
b1 5
b100010101101011 1
0/
b11 2
b10 -
b1000010 $
b1000010 ?
b11111010000000 &
b11111010000000 *
b11 9
b110011110011 .
b110011110010 <
b1010100010110 ;
b100010101101011 :
1+
#160
b1001 A
0+
#170
b11111010000000 8
b10 5
b10 3
b1 @
b110000101000111 1
10
b1 -
b10101101100 4
b1000010 6
17
b110000101000111 :
b1100111100110 )
b1 >
b10101101100 .
b10101101011 <
1+
#180
b1010 A
0+
#190
b10101110101 4
b10101110101 6
07
b0 @
b10101110101 1
00
b1 2
b1000010 )
b10 >
b11111010000000 $
b11111010000000 ?
b10 &
b10 *
b10 9
b10101101101 .
b10101101100 <
bx ;
b10101110101 :
1+
#200
b1011 A
0+
#210
1!
b11111010000000 6
b11 3
b1000010 8
b1011 @
b110101110000001 1
10
b0 -
b10101110110 4
b110101110000001 :
b10101110110 .
b10101110101 <
1+
#220
b1100 A
0+
#230
0!
b10101110111 4
b10101110111 6
b10 3
b11111010000000 8
b1 @
b10010101111011 1
00
b11 2
b10 -
b1000010 $
b1000010 ?
b11111010000000 &
b11111010000000 *
b11 9
b10101110111 .
b10101110110 <
b1010100010110 ;
b10010101111011 :
1+
#240
b1101 A
0+
#250
1!
b11111010000000 6
b1 5
b11 3
b1011 @
b110101110001101 1
10
b1 2
b11 -
b1000010 8
b10101111000 4
bx ;
b110101110001101 :
b11111010000000 $
b11111010000000 ?
b10 &
b10 *
b10 9
b10101111000 .
b10101110111 <
1+
#260
b1110 A
0+
#270
0!
b10101111001 4
b1000010 6
b1000001 8
b1010 @
b110101000000000 1
b0 2
b0 -
b1100111100110 )
b1 >
b1000010 $
b1000010 ?
b11111010000000 &
b11111010000000 *
b11 9
b10101111001 .
b10101111000 <
b1010100010110 ;
b110101000000000 :
1+
#280
b1111 A
0+
#290
b10 5
b10 3
b1 @
b110000101000111 1
b11 2
b1 -
b11111010000000 8
b10101111010 4
b1000001 6
17
b1010010101010 ;
b110000101000111 :
b1000001 $
b1000001 ?
b10101111010 .
b10101111001 <
1+
#300
b10000 A
0+
#310
b10101101101 4
b10101101101 6
07
b0 @
b10101101101 1
00
b1 2
b11 -
b1000001 )
b10 >
b11111010000000 $
b11111010000000 ?
b10 &
b10 *
b10 9
b10101111011 .
b10101111010 <
bx ;
b10101101101 :
1+
#320
b10001 A
0+
#330
b11111010000000 6
17
b11 5
b1 3
b10 8
b1 @
b110000101000111 1
10
b11 2
b1 -
b10101101110 4
b110000101000111 :
b10101101110 .
b10101101101 <
1+
#340
b10010 A
0+
#350
1!
b10101101111 4
b10 6
07
b10 3
b0 @
b110000010000001 1
b1 2
b0 -
b11111010000000 )
b11 >
b10 $
b10 ?
b0 &
b0 *
b1 9
b10101101111 .
b10101101110 <
b10000 ;
b110000010000001 :
1+
#360
b10011 A
0+
#370
0!
b101011100000 6
17
b100 5
b100000110000100 1
00
b0 2
b1 -
b110000100 4
b10 3
b100000110000100 :
b10 &
b10 *
b10 9
b10101110000 .
b10101101111 <
1+
#380
b10100 A
0+
#390
1!
b110000101 4
b10 6
07
b11 3
b110000010000001 1
10
b1 2
b0 -
b101011100000 )
b100 >
b110000101 .
b110000100 <
b110000010000001 :
1+
#400
b10101 A
0+
#410
0!
b10000 8
1'
b1100 @
b110110000000000 1
b0 2
b110000110 4
b11 3
b110110000000000 :
b11 9
b110000110 .
b110000101 <
1+
#420
b10110 A
0+
#430
1!
0'
b110000111 4
b10000 6
b10 8
b1 @
b110000110000000 1
b10000 $
b10000 ?
b110000111 .
b110000110 <
b0 ;
b110000110000000 :
1+
#440
b10111 A
0+
#450
b100 3
b0 @
b1 1
00
1/
b1 2
b110001000 4
b110001000 6
b10000 ;
b1000000000000001 :
b10 $
b10 ?
b110001000 .
b110000111 <
b1 8
b10000 &
b10000 *
1+
#460
b11000 A
0+
#470
0!
b110001001 4
b1 6
b11 3
b0 8
b11 @
b110001100000011 1
10
0/
b11 2
b1 $
b1 ?
b10 &
b10 *
b100 9
b110001001 .
b110001000 <
b110011101111 ;
b110001100000011 :
1+
#480
b11001 A
0+
#490
b10000 8
b1 @
b10000110001101 1
00
b1 2
b11 -
b110001101 4
b110001101 6
b10 3
b10000110001101 :
b0 $
b0 ?
b10000 &
b10000 *
b11 9
b110001010 .
b110001001 <
1+
#500
b11010 A
0+
#510
b110001110 6
1!
b110001110 4
b11 3
b11111111 8
b0 @
b11111111 1
1/
b11 2
b10000 $
b10000 ?
b10 &
b10 *
b10 9
b110001110 .
b110001101 <
b0 ;
b1000000011111111 :
1+
#520
b11011 A
0+
#530
b10000 8
0!
b11111111 6
b11 5
b11 @
b111001100001111 1
10
0/
b10101110000 4
b10 3
b1010000 ;
b111001100001111 :
b11111111 $
b11111111 ?
b10000 &
b10000 *
b11 9
b110001111 .
b110001110 <
1+
#540
b11100 A
0+
#550
1!
b10101110001 4
b10000 6
b11 3
b11111010000000 8
b1011 @
b110101110000001 1
b1 2
b0 -
b11111010000000 )
b11 >
b10000 $
b10000 ?
b10 &
b10 *
b10 9
b10101110001 .
b10101110000 <
b0 ;
b110101110000001 :
1+
#560
b11101 A
0+
#570
0!
17
b100 5
b0 @
b100000110010011 1
00
b11 2
b110010011 4
b101011100100 6
b11 3
bx ;
b100000110010011 :
b11111010000000 $
b11111010000000 ?
b10000 &
b10000 *
b11 9
b10101110010 .
b10101110001 <
1+
#580
b11110 A
0+
#590
1!
b110010100 4
b11111010000000 6
07
b10000 8
b1 @
b110000110000000 1
10
b0 2
b101011100100 )
b100 >
b110010100 .
b110010011 <
b110000110000000 :
1+
#600
b11111 A
0+
#610
b100 3
b0 @
b11111111 1
00
1/
b11 2
b11 -
b110010101 4
b110010101 6
07
b0 ;
b1000000011111111 :
b10000 $
b10000 ?
b110010101 .
b110010100 <
b11111111 8
b11111010000000 &
b11111010000000 *
1+
#620
b0 A
0+
#630
0!
b110010110 4
b11111111 6
b11 3
b10000 8
b11 @
b110001100000011 1
10
0/
b0 -
b11111111 $
b11111111 ?
b10000 &
b10000 *
b100 9
b110010110 .
b110010101 <
b1010000 ;
b110001100000011 :
1+
#640
b1 A
0+
#650
1!
b0 @
b110000010000001 1
b1 2
b10000 8
b110010111 4
b10000 6
b100 3
b0 ;
b110000010000001 :
b10000 $
b10000 ?
b11111010000000 &
b11111010000000 *
b11 9
b110010111 .
b110010110 <
1+
#660
b10 A
0+
#670
b110011000 4
b110011000 6
b101 3
b1000 8
b1000 1
00
1/
b0 2
b10 -
b10000 &
b10000 *
b100 9
b110011000 .
b110010111 <
b1000000000001000 :
1+
#680
b11 A
0+
#690
b1000000000000 8
0!
b1000 6
b1101 @
b110110100000011 1
10
0/
b11 2
b0 -
b110011001 4
b100 3
b110110100000011 :
b1000 $
b1000 ?
b101 9
b110011001 .
b110011000 <
1+
#700
b100 A
0+
#710
b110011010 4
b1000000000000 6
b11 3
b1000000010000 8
b100 @
b110010000000011 1
b1000000000000 $
b1000000000000 ?
b100 9
b110011010 .
b110011001 <
b1000000000000000 ;
b110010000000011 :
1+
#720
b101 A
0+
#730
1!
b1 @
b110000110000000 1
b0 2
b11111010000000 8
b110011011 4
b1000000010000 6
b11 3
b110011000000000 ;
b110000110000000 :
b1000000010000 $
b1000000010000 ?
b11111010000000 &
b11111010000000 *
b11 9
b110011011 .
b110011010 <
1+
#740
b110 A
0+
#750
0!
b101010011 4
b1100111000 6
17
b101 5
b0 @
b100000101010011 1
00
b11 2
b11111010000000 $
b11111010000000 ?
b110011100 .
b110011011 <
bx ;
b100000101010011 :
b11111010000000 8
b1000000010000 &
b1000000010000 *
1+
#760
b111 A
0+
#770
1!
b1000000010000 8
b1 @
b110000110000000 1
10
b0 2
b101010100 4
b11111010000000 6
07
b110000110000000 :
b1100111000 )
b101 >
b101010100 .
b101010011 <
1+
#780
b1000 A
0+
#790
b110011100 4
b1000000010000 6
b100 5
b100 3
b111000110001101 1
b1 2
b11 -
b1000000010000 $
b1000000010000 ?
b101010101 .
b101010100 <
b110011000000000 ;
b111000110001101 :
b11111010000000 8
b11111010000000 &
b11111010000000 *
1+
#800
b1001 A
0+
#810
b0 @
b110000010000001 1
b0 -
b11111010000000 8
b110011101 4
b11111010000000 6
b100 5
b101 3
bx ;
b110000010000001 :
b101011100100 )
b100 >
b11111010000000 $
b11111010000000 ?
b1000000010000 &
b1000000010000 *
b100 9
b110011101 .
b110011100 <
1+
#820
b1010 A
0+
#830
0!
1'
b110011110 4
bx 8
b1100 @
b110110000000000 1
b0 2
b11111010000000 &
b11111010000000 *
b101 9
b110011110 .
b110011101 <
b110110000000000 :
1+
#840
b1011 A
0+
#850
1!
b11111010000000 8
0'
b1 @
b110000110000000 1
b110011111 4
bx 6
b110000110000000 :
bx $
bx ?
b110011111 .
b110011110 <
1+
#860
b1100 A
0+
#870
b110100000 4
b110100000 6
b110 3
b0 @
b1 1
00
1/
b1 2
b11111010000000 $
b11111010000000 ?
b110100000 .
b110011111 <
b1000000000000001 :
b1 8
bx &
bx *
1+
#880
b1101 A
0+
#890
b0 8
0!
b1 6
b11 @
b110001100000011 1
10
0/
b11 2
b110100001 4
b101 3
b110011101111 ;
b110001100000011 :
b1 $
b1 ?
b11111010000000 &
b11111010000000 *
b110 9
b110100001 .
b110100000 <
1+
#900
b1110 A
0+
#910
1!
b110100010 4
b110100010 6
b110 3
b0 @
b0 1
00
1/
b0 2
b0 $
b0 ?
bx &
bx *
b101 9
b110100010 .
b110100001 <
b1000000000000000 :
1+
#920
b1111 A
0+
#930
b1111111111111111 8
0!
b0 6
b111 @
b110011100000011 1
10
0/
b11 2
b110100011 4
b101 3
b110011100000011 :
b0 &
b0 *
b110 9
b110100011 .
b110100010 <
1+
#940
b10000 A
0+
#950
1!
b110100100 4
b110100100 6
b110 3
b11111111 8
b0 @
b11111111 1
00
1/
b11 -
b1111111111111111 $
b1111111111111111 ?
bx &
bx *
b101 9
b110100100 .
b110100011 <
bx ;
b1000000011111111 :
1+
#960
b10001 A
0+
#970
b1111111100000000 8
0!
b11111111 6
b101 @
b110010100000011 1
10
0/
b0 -
b110100101 4
b101 3
b1010000 ;
b110010100000011 :
b11111111 $
b11111111 ?
b1111111111111111 &
b1111111111111111 *
b110 9
b110100101 .
b110100100 <
1+
#980
b10010 A
0+
#990
b110100110 4
b1111111100000000 6
17
b101 5
b100 3
bx 8
b1 @
b110000101000111 1
b1 -
b1111111100000000 $
b1111111100000000 ?
bx &
bx *
b101 9
b110100110 .
b110100101 <
bx ;
b110000101000111 :
1+
#1000
b10011 A
0+
#1010
1!
b110000110000001 1
b1 2
b0 -
b1000000010000 8
b110100111 4
bx 6
07
b101 5
b101 3
b110000110000001 :
b1111111100000000 )
b101 >
bx $
bx ?
b1000000010000 &
b1000000010000 *
b100 9
b110100111 .
b110100110 <
1+
#1020
b10100 A
0+
#1030
0!
b110101000 4
b1000000010000 6
b100 3
bx 8
b101 @
b110010100000011 1
b11 2
b1000000010000 $
b1000000010000 ?
bx &
bx *
b101 9
b110101000 .
b110100111 <
b110011000000000 ;
b110010100000011 :
1+
#1040
b10101 A
0+
#1050
1!
b1111111100000000 8
b100 5
b1011 @
b110101110001101 1
b1 2
b11 -
b110101001 4
bx 6
b101 3
bx ;
b110101110001101 :
bx $
bx ?
b1000000010000 &
b1000000010000 *
b100 9
b110101001 .
b110101000 <
1+
#1060
b10110 A
0+
#1070
0!
b110101010 4
b1111111100000000 6
b100 3
bx00000000 8
b11 @
b110001100000011 1
b11 2
b0 -
b101011100100 )
b100 >
b1111111100000000 $
b1111111100000000 ?
bx &
bx *
b101 9
b110101010 .
b110101001 <
b110001100000011 :
1+
#1080
b10111 A
0+
#1090
b101 @
b110010100000011 1
bx00010000 8
b110101011 4
bx00000000 6
b11 3
b110010100000011 :
bx00000000 $
bx00000000 ?
b1000000010000 &
b1000000010000 *
b100 9
b110101011 .
b110101010 <
1+
#1100
b11000 A
0+
#1110
1!
b110101100 4
bx00010000 6
b11111010000000 8
b1 @
b110000110000000 1
b0 2
bx00010000 $
bx00010000 ?
b11111010000000 &
b11111010000000 *
b11 9
b110101100 .
b110101011 <
b110000110000000 :
1+
#1120
b11001 A
0+
#1130
0!
1(
1"
b10 3
b0 @
b110000000100011 1
b11 2
b110101101 4
b11111010000000 6
b110000000100011 :
b11111010000000 $
b11111010000000 ?
b110101101 .
b110101100 <
b11111010000000 8
bx00010000 &
bx00010000 *
1+
#1140
b11010 A
0+
#1150
0(
0"
b10101110010 4
b11 5
b1 3
b10 8
b1 @
b111000100001111 1
b11 -
b10 &
b10 *
b10 9
b110101110 .
b110101101 <
b111000100001111 :
1+
#1160
b11011 A
0+
#1170
b0 @
b100000101101011 1
00
b10 -
b10 8
b101101011 4
b101011100110 6
17
b100 5
b1 3
b10000 ;
b100000101101011 :
b11111010000000 )
b11 >
b10 $
b10 ?
b0 &
b0 *
b1 9
b10101110011 .
b10101110010 <
1+
#1180
b11100 A
0+
#1190
1!
b101101100 4
b101101100 6
07
b10 3
b1 8
b1 1
1/
b1 2
b0 -
b101011100110 )
b100 >
b101101100 .
b101101011 <
b1000000000000001 :
1+
#1200
b11101 A
0+
#1210
b11 8
0!
b1 6
b11 5
b10 @
b111001000001111 1
10
0/
b11 2
b11 -
b10101110011 4
b1 3
b110011101111 ;
b111001000001111 :
b1 $
b1 ?
b10 &
b10 *
b10 9
b101101101 .
b101101100 <
1+
#1220
b11110 A
0+
#1230
1!
b10101110100 4
b11 6
b10 5
b10 3
b11111010000000 8
b1011 @
b110101110001101 1
b1 2
b11111010000000 )
b11 >
b11 $
b11 ?
b0 &
b0 *
b1 9
b10101110100 .
b10101110011 <
b10000 ;
b110101110001101 :
1+
#1240
b11111 A
0+
#1250
0!
b0 @
b100000101101011 1
00
b11 2
b10 -
b11111010000000 8
b101101011 4
b101011101010 6
17
b11 5
b10 3
bx00010000 ;
b100000101101011 :
b1000001 )
b10 >
b11111010000000 $
b11111010000000 ?
b11 &
b11 *
b10 9
b10101110101 .
b10101110100 <
1+
#1260
b0 A
0+
#1270
1!
b101101100 4
b101101100 6
07
b11 3
b1 8
b1 1
1/
b1 2
b0 -
b101011101010 )
b11 >
b101101100 .
b101101011 <
b1000000000000001 :
1+
#1280
b1 A
0+
#1290
b11111010000001 8
0!
b1 6
b10 5
b10 @
b111001000001111 1
10
0/
b11 2
b11 -
b10101110101 4
b10 3
b110011101111 ;
b111001000001111 :
b1 $
b1 ?
b11111010000000 &
b11111010000000 *
b11 9
b101101101 .
b101101100 <
1+
#1300
b10 A
0+
#1310
1!
b10101110110 4
b11111010000001 6
b11 3
b1000001 8
b1011 @
b110101110000001 1
b1 2
b0 -
b1000001 )
b10 >
b11111010000001 $
b11111010000001 ?
b11 &
b11 *
b10 9
b10101110110 .
b10101110101 <
bx00010000 ;
b110101110000001 :
1+
#1320
b11 A
0+
#1330
0!
b11111010000001 8
b1 @
b10010101111011 1
00
b11 2
b10 -
b10101110111 4
b10101110111 6
07
b10 3
b1010010101010 ;
b10010101111011 :
b1000001 $
b1000001 ?
b11111010000001 &
b11111010000001 *
b11 9
b10101110111 .
b10101110110 <
1+
#1340
b100 A
0+
#1350
1!
b10101111000 4
b11111010000001 6
b1 5
b11 3
b1000001 8
b1011 @
b110101110001101 1
10
b1 2
b11 -
b11111010000001 $
b11111010000001 ?
b11 &
b11 *
b10 9
b10101111000 .
b10101110111 <
bx00010000 ;
b110101110001101 :
1+
#1360
b101 A
0+
#1370
0!
b1010 @
b110101000000000 1
b0 2
b0 -
b1000000 8
b10101111001 4
b1000001 6
b1 5
b11 3
b1010010101010 ;
b110101000000000 :
b1100111100110 )
b1 >
b1000001 $
b1000001 ?
b11111010000001 &
b11111010000001 *
b11 9
b10101111001 .
b10101111000 <
1+
#1380
b110 A
0+
#1390
b10101111010 4
b1000000 6
17
b10 5
b10 3
b11111010000001 8
b1 @
b110000101000111 1
b11 2
b1 -
b1000000 $
b1000000 ?
b10101111010 .
b10101111001 <
b110000101000111 :
1+
#1400
b111 A
0+
#1410
07
b0 @
b10101101101 1
00
b1 2
b11 -
b11111010000001 8
b10101101101 4
b10101101101 6
b10 5
b10 3
bx00010000 ;
b10101101101 :
b1000000 )
b10 >
b11111010000001 $
b11111010000001 ?
b11 &
b11 *
b10 9
b10101111011 .
b10101111010 <
1+
#1420
b1000 A
0+
